partner_tools/__init__.py
partner_tools/config.py
partner_tools/partner_tools.py
partner_tools/auth/__init__.py
partner_tools/auth/auth_info.py
partner_tools/auth/device_code.py
partner_tools/auth/interactive.py
partner_tools/cli/__init__.py
partner_tools/cli/cli.py
partner_tools/cli/controller.py
partner_tools/cli/interactive/__init__.py
partner_tools/cli/interactive/auth_args.py
partner_tools/cli/interactive/autopilot_args.py
partner_tools/cli/interactive/common_args.py
partner_tools/cli/interactive/question_wrapper.py
partner_tools/clients/__init__.py
partner_tools/clients/api.py
partner_tools/models/__init__.py
partner_tools/models/autopilot_device.py
partner_tools/models/customer.py
partner_tools/services/__init__.py
partner_tools/services/base.py
partner_tools/services/customer.py
ms_partner_tools-0.1.1.dist-info/LICENSE.txt
ms_partner_tools-0.1.1.dist-info/METADATA
ms_partner_tools-0.1.1.dist-info/WHEEL
ms_partner_tools-0.1.1.dist-info/entry_points.txt
ms_partner_tools-0.1.1.dist-info/top_level.txt
ms_partner_tools-0.1.1.dist-info/RECORD
