Metadata-Version: 2.1
Name: ms-partner-tools
Version: 0.1.1
Summary: SDK for interacting with the Microsoft Partner Center
Home-page: https://github.com/techstormpc/ms-partner-tools
Author: TechStorm PC
Author-email: nathan@techstormpc.com
License: MIT
Platform: UNKNOWN
Classifier: Development Status :: 2 - Pre-Alpha
Classifier: Intended Audience :: Information Technology
Classifier: Operating System :: OS Independent
Classifier: License :: OSI Approved :: MIT License
Classifier: Programming Language :: Python :: 3 :: Only
Classifier: Programming Language :: Python :: 3
Classifier: Programming Language :: Python :: 3.8
Classifier: Programming Language :: Python :: 3.9
Classifier: Programming Language :: Python :: 3.10
Requires-Dist: click (<8.1,>=8.0)
Requires-Dist: questionary (==1.10.0)
Requires-Dist: requests (==2.27.1)
Requires-Dist: azure-identity (>=1.8.0)
Requires-Dist: pydantic (==1.10.2)
